harwest/__init__.py
harwest/__main__.py
harwest/harwest.py
harwest/lib/abstractworkflow.py
harwest/lib/atcoder/client.py
harwest/lib/atcoder/workflow.py
harwest/lib/codeforces/client.py
harwest/lib/codeforces/workflow.py
harwest/lib/resources/language.json
harwest/lib/resources/readme.template
harwest/lib/utils/config.py
harwest/lib/utils/repository.py
harwest/lib/utils/submissions.py
harwest-0.3.2.dist-info/LICENSE
harwest-0.3.2.dist-info/METADATA
harwest-0.3.2.dist-info/WHEEL
harwest-0.3.2.dist-info/entry_points.txt
harwest-0.3.2.dist-info/top_level.txt
harwest-0.3.2.dist-info/RECORD
