Metadata-Version: 2.1
Name: harwest
Version: 0.3.2
Summary: Harvest code submissions from different platforms to git
Home-page: https://github.com/nileshsah/harwest-tool
Author: Nilesh Sah
Author-email: nilesh.sah13@outlook.com
License: UNKNOWN
Platform: UNKNOWN
Classifier: Programming Language :: Python :: 3
Classifier: License :: OSI Approved :: MIT License
Classifier: Operating System :: OS Independent
Requires-Python: >=3.5
Requires-Dist: gitpython (==3.0.6)
Requires-Dist: gitdb2
Requires-Dist: lxml
Requires-Dist: beautifulsoup4 (==4.8.2)
Requires-Dist: requests
